tvdcn/_C.cpython-312-darwin.so
tvdcn/__init__.py
tvdcn/_version.py
tvdcn/extension.py
tvdcn/utils.py
tvdcn/csrc/tvdcn.cpp
tvdcn/csrc/ops/deform_conv1d.cpp
tvdcn/csrc/ops/deform_conv2d.cpp
tvdcn/csrc/ops/deform_conv3d.cpp
tvdcn/csrc/ops/deform_conv_transpose1d.cpp
tvdcn/csrc/ops/deform_conv_transpose2d.cpp
tvdcn/csrc/ops/deform_conv_transpose3d.cpp
tvdcn/csrc/ops/autocast/deform_conv1d_kernel.cpp
tvdcn/csrc/ops/autocast/deform_conv2d_kernel.cpp
tvdcn/csrc/ops/autocast/deform_conv3d_kernel.cpp
tvdcn/csrc/ops/autocast/deform_conv_transpose1d_kernel.cpp
tvdcn/csrc/ops/autocast/deform_conv_transpose2d_kernel.cpp
tvdcn/csrc/ops/autocast/deform_conv_transpose3d_kernel.cpp
tvdcn/csrc/ops/autograd/deform_conv1d_kernel.cpp
tvdcn/csrc/ops/autograd/deform_conv2d_kernel.cpp
tvdcn/csrc/ops/autograd/deform_conv3d_kernel.cpp
tvdcn/csrc/ops/autograd/deform_conv_transpose1d_kernel.cpp
tvdcn/csrc/ops/autograd/deform_conv_transpose2d_kernel.cpp
tvdcn/csrc/ops/autograd/deform_conv_transpose3d_kernel.cpp
tvdcn/csrc/ops/cpu/deform_conv1d_common_kernels.cpp
tvdcn/csrc/ops/cpu/deform_conv1d_kernel.cpp
tvdcn/csrc/ops/cpu/deform_conv2d_common_kernels.cpp
tvdcn/csrc/ops/cpu/deform_conv2d_kernel.cpp
tvdcn/csrc/ops/cpu/deform_conv3d_common_kernels.cpp
tvdcn/csrc/ops/cpu/deform_conv3d_kernel.cpp
tvdcn/csrc/ops/cpu/deform_conv_transpose1d_kernel.cpp
tvdcn/csrc/ops/cpu/deform_conv_transpose2d_kernel.cpp
tvdcn/csrc/ops/cpu/deform_conv_transpose3d_kernel.cpp
tvdcn/csrc/ops/cuda/deform_conv1d_common_kernels.cu
tvdcn/csrc/ops/cuda/deform_conv1d_kernel.cpp
tvdcn/csrc/ops/cuda/deform_conv2d_common_kernels.cu
tvdcn/csrc/ops/cuda/deform_conv2d_kernel.cpp
tvdcn/csrc/ops/cuda/deform_conv3d_common_kernels.cu
tvdcn/csrc/ops/cuda/deform_conv3d_kernel.cpp
tvdcn/csrc/ops/cuda/deform_conv_transpose1d_kernel.cpp
tvdcn/csrc/ops/cuda/deform_conv_transpose2d_kernel.cpp
tvdcn/csrc/ops/cuda/deform_conv_transpose3d_kernel.cpp
tvdcn/csrc/ops/utils/tensor_utils.cpp
tvdcn/ops/__init__.py
tvdcn/ops/deform_conv.py
tvdcn-1.1.0.dist-info/licenses/LICENSE.txt
tvdcn-1.1.0.dist-info/METADATA
tvdcn-1.1.0.dist-info/WHEEL
tvdcn-1.1.0.dist-info/top_level.txt
tvdcn-1.1.0.dist-info/RECORD
